Scientific/__init__.py
Scientific/Clustering/__init__.py
Scientific/Clustering/kmeans.py
hyperheuristic/__init__.py
hyperheuristic/hyperheuristic.py
NegoTools-0.9.dist-info/METADATA
NegoTools-0.9.dist-info/WHEEL
NegoTools-0.9.dist-info/top_level.txt
NegoTools-0.9.dist-info/RECORD
